[
  {
    "internalName": "HIDDENCUBEWORLDTOPDOWN3D",
    "title": "Hidden Cube World Top-Down 3D",
    "metacriticLink": "/game/pc/hidden-cube-world-top-down-3d",
    "dealID": "AMZnt9gRD90BySxvHuxpG0Vfn9UiiFUiQMYbllvgfhg%3D",
    "storeID": "1",
    "gameID": "250072",
    "salePrice": "4.49",
    "normalPrice": "44.99",
    "isOnSale": "1",
    "savings": "90.020004",
    "metacriticScore": "0",
    "steamRatingText": "Positive",
    "steamRatingPercent": "90",
    "steamRatingCount": "11",
    "steamAppID": "2108760",
    "releaseDate": 1660780800,
    "lastChange": 1664311146,
    "dealRating": "9.9",
    "thumb": "https://cdn.cloudflare.steamstatic.com/steam/apps/2108760/capsule_sm_120.jpg?t=1660827879"
  },
  {
    "internalName": "WITCHEPOCH",
    "title": "Witch Epoch",
    "metacriticLink": "/game/pc/witch-epoch",
    "dealID": "mQjjbv83vy2gXpFO8UK5VcKRs8T2izQ9ksl7q3o48zQ%3D",
    "storeID": "1",
    "gameID": "247796",
    "salePrice": "2.49",
    "normalPrice": "24.99",
    "isOnSale": "1",
    "savings": "90.036014",
    "metacriticScore": "0",
    "steamRatingText": "Positive",
    "steamRatingPercent": "100",
    "steamRatingCount": "11",
    "steamAppID": "2012340",
    "releaseDate": 1655078400,
    "lastChange": 1664237676,
    "dealRating": "9.7",
    "thumb": "https://cdn.cloudflare.steamstatic.com/steam/apps/2012340/capsule_sm_120.jpg?t=1655120766"
  },
  {
    "internalName": "WORKERRIOT",
    "title": "Worker Riot",
    "metacriticLink": "/game/pc/worker-riot",
    "dealID": "uKT6B0TwfJ2Ga%2BRYQF%2FlrPadoKibJ1M9uhbDlZuhCLw%3D",
    "storeID": "1",
    "gameID": "247797",
    "salePrice": "2.49",
    "normalPrice": "24.99",
    "isOnSale": "1",
    "savings": "90.036014",
    "metacriticScore": "0",
    "steamRatingText": "Positive",
    "steamRatingPercent": "100",
    "steamRatingCount": "11",
    "steamAppID": "2013770",
    "releaseDate": 1655078400,
    "lastChange": 1664212356,
    "dealRating": "9.5",
    "thumb": "https://cdn.cloudflare.steamstatic.com/steam/apps/2013770/capsule_sm_120.jpg?t=1655120691"
  },
  {
    "internalName": "ZOMBIENIGHTTERROR",
    "title": "Zombie Night Terror",
    "metacriticLink": "/game/pc/zombie-night-terror",
    "dealID": "kfwmtdgaQCWWgiQOf5nL4d5%2BMuEwy%2Bo5avHGyMJVF4c%3D",
    "storeID": "1",
    "gameID": "154629",
    "salePrice": "1.29",
    "normalPrice": "12.99",
    "isOnSale": "1",
    "savings": "90.069284",
    "metacriticScore": "81",
    "steamRatingText": "Very Positive",
    "steamRatingPercent": "93",
    "steamRatingCount": "2363",
    "steamAppID": "416680",
    "releaseDate": 1468972800,
    "lastChange": 1664232033,
    "dealRating": "9.5",
    "thumb": "https://cdn.cloudflare.steamstatic.com/steam/apps/416680/capsule_sm_120.jpg?t=1582640712"
  },
  {
    "internalName": "IMPULSION",
    "title": "Impulsion",
    "metacriticLink": "/game/pc/impulsion",
    "dealID": "wVSMfNngwSH659CMc6aDUC2A7Bw2rhCjzTXFpggFaLs%3D",
    "storeID": "1",
    "gameID": "189778",
    "salePrice": "1.29",
    "normalPrice": "12.99",
    "isOnSale": "1",
    "savings": "90.069284",
    "metacriticScore": "79",
    "steamRatingText": "Very Positive",
    "steamRatingPercent": "91",
    "steamRatingCount": "99",
    "steamAppID": "811270",
    "releaseDate": 1531958400,
    "lastChange": 1664233182,
    "dealRating": "9.4",
    "thumb": "https://cdn.cloudflare.steamstatic.com/steam/apps/811270/capsule_sm_120.jpg?t=1656515815"
  },
  {
    "internalName": "DUNGEONSOFDREADROCK",
    "title": "Dungeons of Dreadrock",
    "metacriticLink": "/game/pc/dungeons-of-dreadrock",
    "dealID": "BZ7iJIKs3PjdGBLlqhLefsioiMQ5W6ZsvaM4Elnfgqw%3D",
    "storeID": "1",
    "gameID": "241978",
    "salePrice": "1.79",
    "normalPrice": "5.99",
    "isOnSale": "1",
    "savings": "70.116861",
    "metacriticScore": "75",
    "steamRatingText": "Very Positive",
    "steamRatingPercent": "95",
    "steamRatingCount": "133",
    "steamAppID": "1896880",
    "releaseDate": 1647216000,
    "lastChange": 1664232333,
    "dealRating": "9.3",
    "thumb": "https://cdn.cloudflare.steamstatic.com/steam/apps/1896880/capsule_sm_120.jpg?t=1662377037"
  },
  {
    "internalName": "THEADVENTUREPALS",
    "title": "The Adventure Pals",
    "metacriticLink": "/game/pc/the-adventure-pals",
    "dealID": "MeF%2BW%2BXLrynxQDxVkQJj0%2FusUVSRkZv0tf5oYGCuy6w%3D",
    "storeID": "1",
    "gameID": "185506",
    "salePrice": "1.49",
    "normalPrice": "14.99",
    "isOnSale": "1",
    "savings": "90.060040",
    "metacriticScore": "78",
    "steamRatingText": "Very Positive",
    "steamRatingPercent": "94",
    "steamRatingCount": "697",
    "steamAppID": "396710",
    "releaseDate": 1522713600,
    "lastChange": 1664231964,
    "dealRating": "9.3",
    "thumb": "https://cdn.cloudflare.steamstatic.com/steam/apps/396710/capsule_sm_120.jpg?t=1573082510"
  },
  {
    "internalName": "WARHAMMERENDTIMESVERMINTIDE",
    "title": "Warhammer: End Times - Vermintide",
    "metacriticLink": "/game/pc/warhammer-end-times---vermintide",
    "dealID": "IFYr9AIXHCkSKU0rkj1Tl2V1Cvk%2BWPz%2FmGaH2%2F%2BufYc%3D",
    "storeID": "1",
    "gameID": "145156",
    "salePrice": "2.99",
    "normalPrice": "29.99",
    "isOnSale": "1",
    "savings": "90.030010",
    "metacriticScore": "79",
    "steamRatingText": "Very Positive",
    "steamRatingPercent": "82",
    "steamRatingCount": "12506",
    "steamAppID": "235540",
    "releaseDate": 1445558400,
    "lastChange": 1664231418,
    "dealRating": "9.3",
    "thumb": "https://cdn.cloudflare.steamstatic.com/steam/apps/235540/capsule_sm_120.jpg?t=1656431954"
  },
  {
    "internalName": "HAMILTONSGREATADVENTURE",
    "title": "Hamilton's Great Adventure",
    "metacriticLink": "/game/pc/hamiltons-great-adventure",
    "dealID": "x8Kfgl9R76ZwLqlksfLm3JyHByHXnS0v0Szr7FjEwpw%3D",
    "storeID": "1",
    "gameID": "463",
    "salePrice": "0.99",
    "normalPrice": "9.99",
    "isOnSale": "1",
    "savings": "90.090090",
    "metacriticScore": "77",
    "steamRatingText": "Mixed",
    "steamRatingPercent": "68",
    "steamRatingCount": "199",
    "steamAppID": "42140",
    "releaseDate": 1306800000,
    "lastChange": 1664215950,
    "dealRating": "9.3",
    "thumb": "https://cdn.cloudflare.steamstatic.com/steam/apps/42140/capsule_sm_120.jpg?t=1591085088"
  },
  {
    "internalName": "OVERTURE",
    "title": "Overture",
    "metacriticLink": "/game/pc/overture",
    "dealID": "6yfe%2Fx5nycxkYLFJxGV3l1pyE2Y0alWFRIhgnls%2FpTU%3D",
    "storeID": "1",
    "gameID": "140879",
    "salePrice": "0.49",
    "normalPrice": "4.99",
    "isOnSale": "1",
    "savings": "90.180361",
    "metacriticScore": "76",
    "steamRatingText": "Mostly Positive",
    "steamRatingPercent": "72",
    "steamRatingCount": "544",
    "steamAppID": "343100",
    "releaseDate": 1422230400,
    "lastChange": 1664212126,
    "dealRating": "9.3",
    "thumb": "https://cdn.cloudflare.steamstatic.com/steam/apps/343100/capsule_sm_120.jpg?t=1614781615"
  },
  {
    "internalName": "POLYBRIDGE",
    "title": "Poly Bridge",
    "metacriticLink": "/game/pc/poly-bridge",
    "dealID": "E1Otoc%2B7bswCzBTTctrev2zxgsoL5MLd89wK8d%2Bz1S4%3D",
    "storeID": "1",
    "gameID": "144661",
    "salePrice": "0.99",
    "normalPrice": "9.99",
    "isOnSale": "1",
    "savings": "90.090090",
    "metacriticScore": "73",
    "steamRatingText": "Very Positive",
    "steamRatingPercent": "91",
    "steamRatingCount": "13082",
    "steamAppID": "367450",
    "releaseDate": 1468281600,
    "lastChange": 1664231403,
    "dealRating": "9.1",
    "thumb": "https://cdn.cloudflare.steamstatic.com/steam/apps/367450/capsule_sm_120.jpg?t=1567634023"
  },
  {
    "internalName": "PENARIUM",
    "title": "Penarium",
    "metacriticLink": "/game/pc/penarium",
    "dealID": "yhc2eAYs8Pr8%2FJlMqVbFiYkCgAqVOh69ZhIjOEDvr3o%3D",
    "storeID": "1",
    "gameID": "145875",
    "salePrice": "1.49",
    "normalPrice": "9.99",
    "isOnSale": "1",
    "savings": "85.085085",
    "metacriticScore": "80",
    "steamRatingText": "Very Positive",
    "steamRatingPercent": "95",
    "steamRatingCount": "64",
    "steamAppID": "307590",
    "releaseDate": 1442880000,
    "lastChange": 1664236402,
    "dealRating": "9.1",
    "thumb": "https://cdn.cloudflare.steamstatic.com/steam/apps/307590/capsule_sm_120.jpg?t=1655730979"
  },
  {
    "internalName": "VALENTINOROSSITHEGAME",
    "title": "Valentino Rossi The Game",
    "metacriticLink": "/game/pc/valentino-rossi-the-game",
    "dealID": "QYYzXnquARyRhlXiKxCT5aDbZnTOsX0IrKHVZT%2BVeiQ%3D",
    "storeID": "1",
    "gameID": "153893",
    "salePrice": "1.49",
    "normalPrice": "14.99",
    "isOnSale": "1",
    "savings": "90.060040",
    "metacriticScore": "72",
    "steamRatingText": "Very Positive",
    "steamRatingPercent": "81",
    "steamRatingCount": "249",
    "steamAppID": "438430",
    "releaseDate": 1466035200,
    "lastChange": 1664232796,
    "dealRating": "9.0",
    "thumb": "https://cdn.cloudflare.steamstatic.com/steam/apps/438430/capsule_sm_120.jpg?t=1574434309"
  },
  {
    "internalName": "LEADANDGOLDGANGSOFTHEWILDWEST",
    "title": "Lead and Gold: Gangs of the Wild West",
    "metacriticLink": "/game/pc/lead-and-gold-gangs-of-the-wild-west",
    "dealID": "Tq2UG%2Bf7XpVvn0YD07DPtx86ThQEllMAhQMtJjMbT3Q%3D",
    "storeID": "1",
    "gameID": "803",
    "salePrice": "0.99",
    "normalPrice": "9.99",
    "isOnSale": "1",
    "savings": "90.090090",
    "metacriticScore": "70",
    "steamRatingText": "Mostly Positive",
    "steamRatingPercent": "71",
    "steamRatingCount": "859",
    "steamAppID": "42120",
    "releaseDate": 1270684800,
    "lastChange": 1664212180,
    "dealRating": "9.0",
    "thumb": "https://cdn.cloudflare.steamstatic.com/steam/apps/42120/capsule_sm_120.jpg?t=1591079453"
  },
  {
    "internalName": "WAILINGHEIGHTS",
    "title": "Wailing Heights",
    "metacriticLink": "/game/pc/wailing-heights",
    "dealID": "YDv0fq1XfbCi%2FpMu1Mipw6D1dBGyTzbi3aybabKTa%2BI%3D",
    "storeID": "1",
    "gameID": "152113",
    "salePrice": "0.99",
    "normalPrice": "9.99",
    "isOnSale": "1",
    "savings": "90.090090",
    "metacriticScore": "70",
    "steamRatingText": "Mostly Positive",
    "steamRatingPercent": "77",
    "steamRatingCount": "85",
    "steamAppID": "443650",
    "releaseDate": 1461715200,
    "lastChange": 1664212776,
    "dealRating": "9.0",
    "thumb": "https://cdn.cloudflare.steamstatic.com/steam/apps/443650/capsule_sm_120.jpg?t=1599129114"
  },
  {
    "internalName": "BLOODSPORTSTV",
    "title": "Bloodsports.TV",
    "metacriticLink": "/game/pc/bloodsportstv",
    "dealID": "Lw%2F46E8pFB9qRPuJjEzFaLUtecZqujeqxpOUk%2F7OUr8%3D",
    "storeID": "1",
    "gameID": "142796",
    "salePrice": "0.99",
    "normalPrice": "9.99",
    "isOnSale": "1",
    "savings": "90.090090",
    "metacriticScore": "69",
    "steamRatingText": "Very Positive",
    "steamRatingPercent": "81",
    "steamRatingCount": "180",
    "steamAppID": "336420",
    "releaseDate": 1427673600,
    "lastChange": 1664233118,
    "dealRating": "8.9",
    "thumb": "https://cdn.cloudflare.steamstatic.com/steam/apps/336420/capsule_sm_120.jpg?t=1591085167"
  },
  {
    "internalName": "SCALEPLANET",
    "title": "SCALEPLANET",
    "metacriticLink": "/game/pc/scaleplanet",
    "dealID": "GibdBryf9GCUgDGHxoAc%2F2QkJemHlocHHnoYW87Oa0U%3D",
    "storeID": "1",
    "gameID": "247006",
    "salePrice": "4.49",
    "normalPrice": "44.99",
    "isOnSale": "1",
    "savings": "90.020004",
    "metacriticScore": "0",
    "steamRatingText": "Positive",
    "steamRatingPercent": "100",
    "steamRatingCount": "10",
    "steamAppID": "1922360",
    "releaseDate": 1653350400,
    "lastChange": 1663959941,
    "dealRating": "8.9",
    "thumb": "https://cdn.cloudflare.steamstatic.com/steam/apps/1922360/capsule_sm_120.jpg?t=1660745571"
  },
  {
    "internalName": "THEINNERWORLD",
    "title": "The Inner World",
    "metacriticLink": "/game/pc/the-inner-world",
    "dealID": "Hj%2B%2BtuFWB5%2F8YfjBzmprrH5dEtAxye3wgqDDdkpBmew%3D",
    "storeID": "1",
    "gameID": "101835",
    "salePrice": "2.03",
    "normalPrice": "16.99",
    "isOnSale": "1",
    "savings": "88.051795",
    "metacriticScore": "72",
    "steamRatingText": "Very Positive",
    "steamRatingPercent": "90",
    "steamRatingCount": "556",
    "steamAppID": "251430",
    "releaseDate": 1380240000,
    "lastChange": 1664232455,
    "dealRating": "8.8",
    "thumb": "https://cdn.cloudflare.steamstatic.com/steam/apps/251430/capsule_sm_120.jpg?t=1649419091"
  },
  {
    "internalName": "YOKUSISLANDEXPRESS",
    "title": "Yoku's Island Express",
    "metacriticLink": "/game/pc/yokus-island-express",
    "dealID": "3oI2r%2FeoOlMHTR4SAFaFVVRnuQmbD2BPX6VPVE90qGo%3D",
    "storeID": "1",
    "gameID": "186651",
    "salePrice": "3.99",
    "normalPrice": "19.99",
    "isOnSale": "1",
    "savings": "80.040020",
    "metacriticScore": "84",
    "steamRatingText": "Overwhelmingly Positive",
    "steamRatingPercent": "96",
    "steamRatingCount": "2157",
    "steamAppID": "334940",
    "releaseDate": 1527552000,
    "lastChange": 1664231582,
    "dealRating": "8.8",
    "thumb": "https://cdn.cloudflare.steamstatic.com/steam/apps/334940/capsule_sm_120.jpg?t=1638519902"
  },
  {
    "internalName": "THEWAY",
    "title": "The Way",
    "metacriticLink": "/game/pc/the-way",
    "dealID": "JQN3zYhOF1DEYdMmFWCQLLIq0PFBIzC59jbsHvNr2Ns%3D",
    "storeID": "1",
    "gameID": "152810",
    "salePrice": "1.49",
    "normalPrice": "14.99",
    "isOnSale": "1",
    "savings": "90.060040",
    "metacriticScore": "67",
    "steamRatingText": "Very Positive",
    "steamRatingPercent": "83",
    "steamRatingCount": "762",
    "steamAppID": "311010",
    "releaseDate": 1463616000,
    "lastChange": 1664233085,
    "dealRating": "8.8",
    "thumb": "https://cdn.cloudflare.steamstatic.com/steam/apps/311010/capsule_sm_120.jpg?t=1663259678"
  },
  {
    "internalName": "THENEXTPENELOPE",
    "title": "The Next Penelope",
    "metacriticLink": "/game/pc/the-next-penelope",
    "dealID": "1w0Q%2BGPAAgMe8QP8lFX5TGO8kH%2FQ%2BF5Qmb5K0MYoE%2FU%3D",
    "storeID": "1",
    "gameID": "141090",
    "salePrice": "2.59",
    "normalPrice": "12.99",
    "isOnSale": "1",
    "savings": "80.061586",
    "metacriticScore": "82",
    "steamRatingText": "Mostly Positive",
    "steamRatingPercent": "73",
    "steamRatingCount": "120",
    "steamAppID": "332250",
    "releaseDate": 1432857600,
    "lastChange": 1664215880,
    "dealRating": "8.8",
    "thumb": "https://cdn.cloudflare.steamstatic.com/steam/apps/332250/capsule_sm_120.jpg?t=1602168342"
  },
  {
    "internalName": "ECHELON",
    "title": "Echelon",
    "metacriticLink": "/game/pc/echelon",
    "dealID": "exYdqKf47ySYqhzXeEkVx5KFhRdCxqRC2iyvJ1dRYvc%3D",
    "storeID": "1",
    "gameID": "116146",
    "salePrice": "0.59",
    "normalPrice": "3.99",
    "isOnSale": "1",
    "savings": "85.213033",
    "metacriticScore": "70",
    "steamRatingText": "Mixed",
    "steamRatingPercent": "42",
    "steamRatingCount": "112",
    "steamAppID": "311080",
    "releaseDate": 989971200,
    "lastChange": 1664238683,
    "dealRating": "8.8",
    "thumb": "https://cdn.cloudflare.steamstatic.com/steam/apps/311080/capsule_sm_120.jpg?t=1659624684"
  },
  {
    "internalName": "RIDE2",
    "title": "Ride 2",
    "metacriticLink": "/game/pc/ride-2",
    "dealID": "InnKKEIb%2FqfKouN%2Bax%2BjKaNmOL143Xpp1Rs7jiiLeFY%3D",
    "storeID": "1",
    "gameID": "153995",
    "salePrice": "2.99",
    "normalPrice": "29.99",
    "isOnSale": "1",
    "savings": "90.030010",
    "metacriticScore": "67",
    "steamRatingText": "Very Positive",
    "steamRatingPercent": "86",
    "steamRatingCount": "2038",
    "steamAppID": "477770",
    "releaseDate": 1475798400,
    "lastChange": 1664231867,
    "dealRating": "8.8",
    "thumb": "https://cdn.cloudflare.steamstatic.com/steam/apps/477770/capsule_sm_120.jpg?t=1576507292"
  },
  {
    "internalName": "WRC4FIAWORLDRALLYCHAMPIONSHIP",
    "title": "WRC 4 FIA World Rally Championship",
    "metacriticLink": "/game/pc/wrc-4-fia-world-rally-championship",
    "dealID": "%2FpwayN8ANjcCcLkpqupgUGS3REdTxpARwRw5X9xNaX0%3D",
    "storeID": "1",
    "gameID": "102499",
    "salePrice": "0.99",
    "normalPrice": "9.99",
    "isOnSale": "1",
    "savings": "90.090090",
    "metacriticScore": "64",
    "steamRatingText": "Mostly Positive",
    "steamRatingPercent": "73",
    "steamRatingCount": "1058",
    "steamAppID": "256330",
    "releaseDate": 1382659200,
    "lastChange": 1664233255,
    "dealRating": "8.8",
    "thumb": "https://cdn.cloudflare.steamstatic.com/steam/apps/256330/capsule_sm_120.jpg?t=1594977488"
  },
  {
    "internalName": "PACMANCHAMPIONSHIPEDITIONDX",
    "title": "PACMAN Championship Edition DX",
    "metacriticLink": "/game/pc/pac-man-championship-edition-dx-+",
    "dealID": "r60iwi8O7aguAFRfS%2FCU2PuNpiRugT7KvpWwJr54hE0%3D",
    "storeID": "1",
    "gameID": "106942",
    "salePrice": "2.49",
    "normalPrice": "9.99",
    "isOnSale": "1",
    "savings": "75.075075",
    "metacriticScore": "86",
    "steamRatingText": "Overwhelmingly Positive",
    "steamRatingPercent": "96",
    "steamRatingCount": "4025",
    "steamAppID": "236450",
    "releaseDate": 1379980800,
    "lastChange": 1664231693,
    "dealRating": "8.7",
    "thumb": "https://cdn.cloudflare.steamstatic.com/steam/apps/236450/capsule_sm_120.jpg?t=1580311291"
  },
  {
    "internalName": "SUMMERCATCHERS",
    "title": "Summer Catchers",
    "metacriticLink": "/game/pc/summer-catchers",
    "dealID": "DC47J4Tid9Drb2ECNBpIsK7RUrwN2WgpBcqfDdBf0cg%3D",
    "storeID": "1",
    "gameID": "203239",
    "salePrice": "1.19",
    "normalPrice": "11.99",
    "isOnSale": "1",
    "savings": "90.075063",
    "metacriticScore": "61",
    "steamRatingText": "Very Positive",
    "steamRatingPercent": "81",
    "steamRatingCount": "155",
    "steamAppID": "908050",
    "releaseDate": 1563235200,
    "lastChange": 1664233227,
    "dealRating": "8.7",
    "thumb": "https://cdn.cloudflare.steamstatic.com/steam/apps/908050/capsule_sm_120.jpg?t=1644117017"
  },
  {
    "internalName": "THESTATION",
    "title": "The Station",
    "metacriticLink": "/game/pc/the-station",
    "dealID": "I5yXqy3tz9hKDMc3MIVJxGd0YIJFohLmByB5sqOy2vc%3D",
    "storeID": "1",
    "gameID": "164781",
    "salePrice": "2.24",
    "normalPrice": "14.99",
    "isOnSale": "1",
    "savings": "85.056704",
    "metacriticScore": "72",
    "steamRatingText": "Very Positive",
    "steamRatingPercent": "86",
    "steamRatingCount": "779",
    "steamAppID": "565120",
    "releaseDate": 1518998400,
    "lastChange": 1664232417,
    "dealRating": "8.6",
    "thumb": "https://cdn.cloudflare.steamstatic.com/steam/apps/565120/capsule_sm_120.jpg?t=1543253743"
  },
  {
    "internalName": "HACKNET",
    "title": "Hacknet",
    "metacriticLink": "/game/pc/hacknet",
    "dealID": "cNO6jjogPpy0yrfcHQNbnlNSmM12wiiCpMmk%2FoAtuAs%3D",
    "storeID": "1",
    "gameID": "145040",
    "salePrice": "1.49",
    "normalPrice": "9.99",
    "isOnSale": "1",
    "savings": "85.085085",
    "metacriticScore": "82",
    "steamRatingText": "Very Positive",
    "steamRatingPercent": "93",
    "steamRatingCount": "12892",
    "steamAppID": "365450",
    "releaseDate": 1439337600,
    "lastChange": 1663876816,
    "dealRating": "8.6",
    "thumb": "https://cdn.cloudflare.steamstatic.com/steam/apps/365450/capsule_sm_120.jpg?t=1659333689"
  },
  {
    "internalName": "WARHAMMERVERMINTIDE2",
    "title": "Warhammer: Vermintide 2",
    "metacriticLink": "/game/pc/warhammer-vermintide-2",
    "dealID": "WsGdr8u7VzKVcEhPy%2BuEqhvHQegMgCeyKlIthyE7rWI%3D",
    "storeID": "1",
    "gameID": "174250",
    "salePrice": "5.99",
    "normalPrice": "29.99",
    "isOnSale": "1",
    "savings": "80.026676",
    "metacriticScore": "82",
    "steamRatingText": "Very Positive",
    "steamRatingPercent": "83",
    "steamRatingCount": "66497",
    "steamAppID": "552500",
    "releaseDate": 1520467200,
    "lastChange": 1664231067,
    "dealRating": "8.6",
    "thumb": "https://cdn.cloudflare.steamstatic.com/steam/apps/552500/capsule_sm_120.jpg?t=1661422117"
  },
  {
    "internalName": "SUPERMAGBOT",
    "title": "Super Magbot",
    "metacriticLink": "/game/pc/super-magbot",
    "dealID": "dNCFcCcp%2BYyH0S3U9Wgy3OHMaAfnOMtrb6ReEvyLP0k%3D",
    "storeID": "1",
    "gameID": "231293",
    "salePrice": "4.49",
    "normalPrice": "17.99",
    "isOnSale": "1",
    "savings": "75.041690",
    "metacriticScore": "80",
    "steamRatingText": "Very Positive",
    "steamRatingPercent": "93",
    "steamRatingCount": "102",
    "steamAppID": "1205170",
    "releaseDate": 1624320000,
    "lastChange": 1664232711,
    "dealRating": "8.6",
    "thumb": "https://cdn.cloudflare.steamstatic.com/steam/apps/1205170/capsule_sm_120.jpg?t=1661365513"
  },
  {
    "internalName": "GROTTO",
    "title": "Grotto",
    "metacriticLink": "/game/pc/grotto",
    "dealID": "nbOmibJCcusj5vCsKIV2ep0k3PAZcneu4ElmJtUmMW4%3D",
    "storeID": "1",
    "gameID": "236049",
    "salePrice": "3.89",
    "normalPrice": "12.99",
    "isOnSale": "1",
    "savings": "70.053888",
    "metacriticScore": "75",
    "steamRatingText": "Very Positive",
    "steamRatingPercent": "95",
    "steamRatingCount": "92",
    "steamAppID": "1538850",
    "releaseDate": 1635206400,
    "lastChange": 1664232085,
    "dealRating": "8.6",
    "thumb": "https://cdn.cloudflare.steamstatic.com/steam/apps/1538850/capsule_sm_120.jpg?t=1639604895"
  },
  {
    "internalName": "SPLASHER",
    "title": "Splasher",
    "metacriticLink": "/game/pc/splasher",
    "dealID": "aN8Pts0iKYHPB5E4ylPqEAydB4jWBv1q1uEQ%2FlScpDY%3D",
    "storeID": "1",
    "gameID": "145115",
    "salePrice": "2.99",
    "normalPrice": "14.99",
    "isOnSale": "1",
    "savings": "80.053369",
    "metacriticScore": "79",
    "steamRatingText": "Very Positive",
    "steamRatingPercent": "95",
    "steamRatingCount": "398",
    "steamAppID": "446840",
    "releaseDate": 1486425600,
    "lastChange": 1664232367,
    "dealRating": "8.6",
    "thumb": "https://cdn.cloudflare.steamstatic.com/steam/apps/446840/capsule_sm_120.jpg?t=1656581950"
  },
  {
    "internalName": "ANARCUTE",
    "title": "Anarcute",
    "metacriticLink": "/game/pc/anarcute",
    "dealID": "C6jS0cMOJaii7ZlifRiOshgANjEMhPqCHATiC3PzfnI%3D",
    "storeID": "1",
    "gameID": "154826",
    "salePrice": "2.99",
    "normalPrice": "14.99",
    "isOnSale": "1",
    "savings": "80.053369",
    "metacriticScore": "79",
    "steamRatingText": "Very Positive",
    "steamRatingPercent": "93",
    "steamRatingCount": "350",
    "steamAppID": "390720",
    "releaseDate": 1468281600,
    "lastChange": 1664232447,
    "dealRating": "8.6",
    "thumb": "https://cdn.cloudflare.steamstatic.com/steam/apps/390720/capsule_sm_120.jpg?t=1592923256"
  },
  {
    "internalName": "TOWAGAAMONGSHADOWS",
    "title": "Towaga: Among Shadows",
    "metacriticLink": "/game/pc/towaga-among-shadows",
    "dealID": "5dgOBvapV9C9h6U1QPFXOIX6KpK1BXN4mt67h%2BjW0%2B0%3D",
    "storeID": "1",
    "gameID": "218228",
    "salePrice": "1.49",
    "normalPrice": "14.99",
    "isOnSale": "1",
    "savings": "90.060040",
    "metacriticScore": "58",
    "steamRatingText": "Positive",
    "steamRatingPercent": "89",
    "steamRatingCount": "37",
    "steamAppID": "907600",
    "releaseDate": 1594684800,
    "lastChange": 1664211902,
    "dealRating": "8.6",
    "thumb": "https://cdn.cloudflare.steamstatic.com/steam/apps/907600/capsule_sm_120.jpg?t=1656574465"
  },
  {
    "internalName": "BASHTHEPARTY",
    "title": "Bash The Party",
    "metacriticLink": "/game/pc/bash-the-party",
    "dealID": "V6R2CBkhzUIjG5gq2v9fbcaaN7g7IXnECoI%2BoBfUt1I%3D",
    "storeID": "1",
    "gameID": "249127",
    "salePrice": "3.74",
    "normalPrice": "14.99",
    "isOnSale": "1",
    "savings": "75.050033",
    "metacriticScore": "0",
    "steamRatingText": null,
    "steamRatingPercent": "0",
    "steamRatingCount": "0",
    "steamAppID": "1939770",
    "releaseDate": 1658448000,
    "lastChange": 1664221518,
    "dealRating": "8.5",
    "thumb": "https://cdn.cloudflare.steamstatic.com/steam/apps/1939770/capsule_sm_120.jpg?t=1658473557"
  },
  {
    "internalName": "ECHELONWINDWARRIORS",
    "title": "Echelon Wind Warriors",
    "metacriticLink": "/game/pc/echelon-wind-warriors",
    "dealID": "UDwNFoVDxW3zx%2Bp4FbiEd5RtV7bG%2BZCNOwc72lF%2FdfI%3D",
    "storeID": "1",
    "gameID": "3155",
    "salePrice": "0.59",
    "normalPrice": "3.99",
    "isOnSale": "1",
    "savings": "85.213033",
    "metacriticScore": "63",
    "steamRatingText": "Mixed",
    "steamRatingPercent": "68",
    "steamRatingCount": "74",
    "steamAppID": "311100",
    "releaseDate": 1076284800,
    "lastChange": 1664238725,
    "dealRating": "8.5",
    "thumb": "https://cdn.cloudflare.steamstatic.com/steam/apps/311100/capsule_sm_120.jpg?t=1659624705"
  },
  {
    "internalName": "FEUDALALLOY",
    "title": "Feudal Alloy",
    "metacriticLink": "/game/pc/feudal-alloy",
    "dealID": "Y%2Bvzm%2FzwLDr3I5AXt68ymlzCd7dzfm3dFiqEjbPwflo%3D",
    "storeID": "1",
    "gameID": "196930",
    "salePrice": "1.69",
    "normalPrice": "16.99",
    "isOnSale": "1",
    "savings": "90.052972",
    "metacriticScore": "76",
    "steamRatingText": "Mixed",
    "steamRatingPercent": "68",
    "steamRatingCount": "535",
    "steamAppID": "699670",
    "releaseDate": 1547683200,
    "lastChange": 1663801168,
    "dealRating": "8.5",
    "thumb": "https://cdn.cloudflare.steamstatic.com/steam/apps/699670/capsule_sm_120.jpg?t=1571849884"
  },
  {
    "internalName": "TINYTROOPERS",
    "title": "Tiny Troopers",
    "metacriticLink": "/game/pc/tiny-troopers",
    "dealID": "3wWkSXp3T7gUr42J8xARnFOFkwxj5CxAR39NfZZBRlo%3D",
    "storeID": "1",
    "gameID": "88886",
    "salePrice": "0.59",
    "normalPrice": "4.99",
    "isOnSale": "1",
    "savings": "88.176353",
    "metacriticScore": "57",
    "steamRatingText": "Very Positive",
    "steamRatingPercent": "81",
    "steamRatingCount": "954",
    "steamAppID": "216110",
    "releaseDate": 1345766400,
    "lastChange": 1664233566,
    "dealRating": "8.4",
    "thumb": "https://cdn.cloudflare.steamstatic.com/steam/apps/216110/capsule_sm_120.jpg?t=1599050479"
  },
  {
    "internalName": "KRATER",
    "title": "Krater",
    "metacriticLink": "/game/pc/krater",
    "dealID": "zRRi9Eu3M6BzbsbmcfgDqKMDXCYCmRGr%2FqTZlTkoZd0%3D",
    "storeID": "1",
    "gameID": "87964",
    "salePrice": "1.49",
    "normalPrice": "14.99",
    "isOnSale": "1",
    "savings": "90.060040",
    "metacriticScore": "52",
    "steamRatingText": "Mixed",
    "steamRatingPercent": "56",
    "steamRatingCount": "590",
    "steamAppID": "42170",
    "releaseDate": 1339459200,
    "lastChange": 1664236753,
    "dealRating": "8.4",
    "thumb": "https://cdn.cloudflare.steamstatic.com/steam/apps/42170/capsule_sm_120.jpg?t=1591085012"
  },
  {
    "internalName": "PHANTARUK",
    "title": "Phantaruk",
    "metacriticLink": "/game/pc/phantaruk",
    "dealID": "RzsTUo1Lu%2Be3a%2BD93pvYM6Hw5STrFQhZeq7uW13BbZA%3D",
    "storeID": "1",
    "gameID": "157494",
    "salePrice": "0.54",
    "normalPrice": "4.99",
    "isOnSale": "1",
    "savings": "89.178357",
    "metacriticScore": "53",
    "steamRatingText": "Mixed",
    "steamRatingPercent": "59",
    "steamRatingCount": "88",
    "steamAppID": "468930",
    "releaseDate": 1471305600,
    "lastChange": 1664216847,
    "dealRating": "8.4",
    "thumb": "https://cdn.cloudflare.steamstatic.com/steam/apps/468930/capsule_sm_120.jpg?t=1663259600"
  },
  {
    "internalName": "AGEOFWONDERSSHADOWMAGIC",
    "title": "Age of Wonders Shadow Magic",
    "metacriticLink": "/game/pc/age-of-wonders-shadow-magic",
    "dealID": "YhNhR4gcCDHTAyVGnWD1fuHoPAQrOApCnMh1gyPoInc%3D",
    "storeID": "1",
    "gameID": "391",
    "salePrice": "2.49",
    "normalPrice": "9.99",
    "isOnSale": "1",
    "savings": "75.075075",
    "metacriticScore": "82",
    "steamRatingText": "Very Positive",
    "steamRatingPercent": "89",
    "steamRatingCount": "420",
    "steamAppID": "61520",
    "releaseDate": 1059091200,
    "lastChange": 1664232394,
    "dealRating": "8.4",
    "thumb": "https://cdn.cloudflare.steamstatic.com/steam/apps/61520/capsule_sm_120.jpg?t=1504268411"
  },
  {
    "internalName": "THEGALACTICJUNKERS",
    "title": "The Galactic Junkers",
    "metacriticLink": "/game/pc/the-galactic-junkers",
    "dealID": "wFJUPwDZsYO2pzRSmXsp8l%2FavjDG5tsBidh2JHTzYyo%3D",
    "storeID": "1",
    "gameID": "247204",
    "salePrice": "4.24",
    "normalPrice": "16.99",
    "isOnSale": "1",
    "savings": "75.044144",
    "metacriticScore": "0",
    "steamRatingText": null,
    "steamRatingPercent": "0",
    "steamRatingCount": "0",
    "steamAppID": "1243160",
    "releaseDate": 1656547200,
    "lastChange": 1664218153,
    "dealRating": "8.4",
    "thumb": "https://cdn.cloudflare.steamstatic.com/steam/apps/1243160/capsule_sm_120.jpg?t=1656608083"
  },
  {
    "internalName": "SHING",
    "title": "Shing!",
    "metacriticLink": "/game/pc/shing!",
    "dealID": "cOfERsQQUFssiNFqNlbMmSCcmGCGM3NThq2eYH7eTpg%3D",
    "storeID": "1",
    "gameID": "219742",
    "salePrice": "1.99",
    "normalPrice": "19.99",
    "isOnSale": "1",
    "savings": "90.045023",
    "metacriticScore": "52",
    "steamRatingText": "Mostly Positive",
    "steamRatingPercent": "79",
    "steamRatingCount": "181",
    "steamAppID": "1103730",
    "releaseDate": 1598572800,
    "lastChange": 1664232929,
    "dealRating": "8.4",
    "thumb": "https://cdn.cloudflare.steamstatic.com/steam/apps/1103730/capsule_sm_120.jpg?t=1637652329"
  },
  {
    "internalName": "HORIZONCHASETURBO",
    "title": "Horizon Chase Turbo",
    "metacriticLink": "/game/pc/horizon-chase-turbo",
    "dealID": "N9%2FVeFgKYqQnrLVZO7mBSqSxWfeXfOj2Lp%2BfmlhDweI%3D",
    "storeID": "1",
    "gameID": "187038",
    "salePrice": "3.99",
    "normalPrice": "19.99",
    "isOnSale": "1",
    "savings": "80.040020",
    "metacriticScore": "76",
    "steamRatingText": "Overwhelmingly Positive",
    "steamRatingPercent": "95",
    "steamRatingCount": "3006",
    "steamAppID": "389140",
    "releaseDate": 1526342400,
    "lastChange": 1664231337,
    "dealRating": "8.4",
    "thumb": "https://cdn.cloudflare.steamstatic.com/steam/apps/389140/capsule_sm_120.jpg?t=1660673287"
  },
  {
    "internalName": "BIOSHOCKINFINITE",
    "title": "BioShock Infinite",
    "metacriticLink": "/game/pc/bioshock-infinite",
    "dealID": "X8sebHhbc1Ga0dTkgg59WgyM506af9oNZZJLU9uSrX8%3D",
    "storeID": "1",
    "gameID": "93503",
    "salePrice": "7.49",
    "normalPrice": "29.99",
    "isOnSale": "1",
    "savings": "75.025008",
    "metacriticScore": "94",
    "steamRatingText": "Very Positive",
    "steamRatingPercent": "94",
    "steamRatingCount": "94926",
    "steamAppID": "8870",
    "releaseDate": 1364169600,
    "lastChange": 1663622425,
    "dealRating": "8.4",
    "thumb": "https://cdn.cloudflare.steamstatic.com/steam/apps/8870/capsule_sm_120.jpg?t=1602794480"
  },
  {
    "internalName": "FAIRSTRIKE",
    "title": "Fair Strike",
    "metacriticLink": "/game/pc/fair-strike",
    "dealID": "LWJ%2FIJui8ErmKrjMiPwLlwnPe6wQzoqJIIwzGK9vHK4%3D",
    "storeID": "1",
    "gameID": "143370",
    "salePrice": "0.59",
    "normalPrice": "3.99",
    "isOnSale": "1",
    "savings": "85.213033",
    "metacriticScore": "56",
    "steamRatingText": "Mostly Positive",
    "steamRatingPercent": "73",
    "steamRatingCount": "57",
    "steamAppID": "352120",
    "releaseDate": 1076371200,
    "lastChange": 1664237203,
    "dealRating": "8.3",
    "thumb": "https://cdn.cloudflare.steamstatic.com/steam/apps/352120/capsule_sm_120.jpg?t=1659528517"
  },
  {
    "internalName": "SCIFANTASYDEFENCE",
    "title": "Sci-Fantasy Defence",
    "metacriticLink": "/game/pc/sci-fantasy-defence",
    "dealID": "u%2BEIIrrKCvXyKKttLmFSI%2BOVo5%2FgtfWM%2BLTW%2BxTluI8%3D",
    "storeID": "1",
    "gameID": "241946",
    "salePrice": "2.99",
    "normalPrice": "14.99",
    "isOnSale": "1",
    "savings": "80.053369",
    "metacriticScore": "0",
    "steamRatingText": null,
    "steamRatingPercent": "0",
    "steamRatingCount": "0",
    "steamAppID": "1650430",
    "releaseDate": 1647216000,
    "lastChange": 1664221044,
    "dealRating": "8.3",
    "thumb": "https://cdn.cloudflare.steamstatic.com/steam/apps/1650430/capsule_sm_120_alt_assets_0.jpg?t=1663738947"
  },
  {
    "internalName": "PLANETALPHA",
    "title": "PLANET ALPHA",
    "metacriticLink": "/game/pc/planet-alpha",
    "dealID": "BtUobhOzJav7HHu9hP2PYLusAxcZnrlgE8ppAdat%2B%2B8%3D",
    "storeID": "1",
    "gameID": "190944",
    "salePrice": "3.99",
    "normalPrice": "19.99",
    "isOnSale": "1",
    "savings": "80.040020",
    "metacriticScore": "72",
    "steamRatingText": "Mostly Positive",
    "steamRatingPercent": "78",
    "steamRatingCount": "454",
    "steamAppID": "485030",
    "releaseDate": 1536019200,
    "lastChange": 1664258079,
    "dealRating": "8.3",
    "thumb": "https://cdn.cloudflare.steamstatic.com/steam/apps/485030/capsule_sm_120.jpg?t=1599472756"
  },
  {
    "internalName": "HELICOPTER20",
    "title": "helicopter 2.0",
    "metacriticLink": "/game/pc/helicopter-20",
    "dealID": "OJQMB6yFL2AbGTgXTA2xrufnws5iAky0EIC2ymIN47c%3D",
    "storeID": "1",
    "gameID": "239065",
    "salePrice": "2.99",
    "normalPrice": "29.99",
    "isOnSale": "1",
    "savings": "90.030010",
    "metacriticScore": "0",
    "steamRatingText": "Positive",
    "steamRatingPercent": "90",
    "steamRatingCount": "11",
    "steamAppID": "1849930",
    "releaseDate": 1641168000,
    "lastChange": 1663959704,
    "dealRating": "8.3",
    "thumb": "https://cdn.cloudflare.steamstatic.com/steam/apps/1849930/capsule_sm_120.jpg?t=1659012581"
  },
  {
    "internalName": "AURIONLEGACYOFTHEKORIODAN",
    "title": "Aurion: Legacy of the Kori-Odan",
    "metacriticLink": "/game/pc/aurion-legacy-of-the-kori-odan",
    "dealID": "hLr5sPe5sKcl1%2BN9zO5dNnggvJt0tBiXYe1tZKKQULs%3D",
    "storeID": "1",
    "gameID": "150918",
    "salePrice": "2.99",
    "normalPrice": "14.99",
    "isOnSale": "1",
    "savings": "80.053369",
    "metacriticScore": "70",
    "steamRatingText": "Very Positive",
    "steamRatingPercent": "87",
    "steamRatingCount": "102",
    "steamAppID": "368080",
    "releaseDate": 1460592000,
    "lastChange": 1664257891,
    "dealRating": "8.3",
    "thumb": "https://cdn.cloudflare.steamstatic.com/steam/apps/368080/capsule_sm_120.jpg?t=1656698454"
  },
  {
    "internalName": "DEMETRIOSTHEBIGCYNICALADVENTURE",
    "title": "Demetrios: The BIG Cynical Adventure",
    "metacriticLink": "/game/pc/demetrios---the-big-cynical-adventure",
    "dealID": "pzLNOOVebgsVdm%2BUF9f12p6v53A7449TGV00xulJvKI%3D",
    "storeID": "1",
    "gameID": "153046",
    "salePrice": "1.99",
    "normalPrice": "9.99",
    "isOnSale": "1",
    "savings": "80.080080",
    "metacriticScore": "72",
    "steamRatingText": "Very Positive",
    "steamRatingPercent": "81",
    "steamRatingCount": "212",
    "steamAppID": "451570",
    "releaseDate": 1464652800,
    "lastChange": 1664232969,
    "dealRating": "8.3",
    "thumb": "https://cdn.cloudflare.steamstatic.com/steam/apps/451570/capsule_sm_120.jpg?t=1653989384"
  },
  {
    "internalName": "THESTILLNESSOFTHEWIND",
    "title": "The Stillness of the Wind",
    "metacriticLink": "/game/pc/the-stillness-of-the-wind",
    "dealID": "9uN3czy0MX7pWHzX%2FGf83ikQpg3Bx7NpVnfIxYo7FjQ%3D",
    "storeID": "1",
    "gameID": "198394",
    "salePrice": "1.94",
    "normalPrice": "12.99",
    "isOnSale": "1",
    "savings": "85.065435",
    "metacriticScore": "76",
    "steamRatingText": "Mostly Positive",
    "steamRatingPercent": "77",
    "steamRatingCount": "784",
    "steamAppID": "828900",
    "releaseDate": 1549497600,
    "lastChange": 1663877395,
    "dealRating": "8.2",
    "thumb": "https://cdn.cloudflare.steamstatic.com/steam/apps/828900/capsule_sm_120.jpg?t=1623115809"
  },
  {
    "internalName": "SHADOWTACTICSBLADESOFTHESHOGUN",
    "title": "Shadow Tactics: Blades of the Shogun",
    "metacriticLink": "/game/pc/shadow-tactics-blades-of-the-shogun",
    "dealID": "j2lexFQ%2Fx%2FOeqECYZgxWgBxj7YX3hcQs0N3Y8mn8kHk%3D",
    "storeID": "1",
    "gameID": "158443",
    "salePrice": "3.99",
    "normalPrice": "39.99",
    "isOnSale": "1",
    "savings": "90.022506",
    "metacriticScore": "85",
    "steamRatingText": "Overwhelmingly Positive",
    "steamRatingPercent": "96",
    "steamRatingCount": "25818",
    "steamAppID": "418240",
    "releaseDate": 1480982400,
    "lastChange": 1663350359,
    "dealRating": "8.2",
    "thumb": "https://cdn.cloudflare.steamstatic.com/steam/apps/418240/capsule_sm_120.jpg?t=1662471039"
  },
  {
    "internalName": "AEONDRIVE",
    "title": "Aeon Drive",
    "metacriticLink": "/game/pc/aeon-drive",
    "dealID": "aAfMq61xORo6e%2Fh6WmSHig%2BpaPyvCPuaFGZhpWfPYL4%3D",
    "storeID": "1",
    "gameID": "235242",
    "salePrice": "5.09",
    "normalPrice": "14.99",
    "isOnSale": "1",
    "savings": "66.044029",
    "metacriticScore": "77",
    "steamRatingText": "Mostly Positive",
    "steamRatingPercent": "76",
    "steamRatingCount": "51",
    "steamAppID": "1252240",
    "releaseDate": 1632960000,
    "lastChange": 1664212375,
    "dealRating": "8.2",
    "thumb": "https://cdn.cloudflare.steamstatic.com/steam/apps/1252240/capsule_sm_120.jpg?t=1638194046"
  },
  {
    "internalName": "MISSINGPERSONS",
    "title": "Missing Persons",
    "metacriticLink": "/game/pc/missing-persons",
    "dealID": "2q6azAnjg1Vl4YGYFsusiadrpO%2B1FqLVHNAAJCbyosA%3D",
    "storeID": "1",
    "gameID": "250071",
    "salePrice": "5.99",
    "normalPrice": "19.99",
    "isOnSale": "1",
    "savings": "70.035018",
    "metacriticScore": "0",
    "steamRatingText": null,
    "steamRatingPercent": "0",
    "steamRatingCount": "0",
    "steamAppID": "1970510",
    "releaseDate": 1660780800,
    "lastChange": 1664218359,
    "dealRating": "8.2",
    "thumb": "https://cdn.cloudflare.steamstatic.com/steam/apps/1970510/capsule_sm_120.jpg?t=1663462193"
  },
  {
    "internalName": "FREAKINGMEATBAGS",
    "title": "Freaking Meatbags",
    "metacriticLink": "/game/pc/freaking-meatbags",
    "dealID": "QimxPUOwGlcL0HXyP7dztjr2VLqwlHos%2FOflg5rvnCs%3D",
    "storeID": "1",
    "gameID": "109515",
    "salePrice": "1.99",
    "normalPrice": "9.99",
    "isOnSale": "1",
    "savings": "80.080080",
    "metacriticScore": "69",
    "steamRatingText": "Very Positive",
    "steamRatingPercent": "83",
    "steamRatingCount": "65",
    "steamAppID": "297060",
    "releaseDate": 1400544000,
    "lastChange": 1664233284,
    "dealRating": "8.1",
    "thumb": "https://cdn.cloudflare.steamstatic.com/steam/apps/297060/capsule_sm_120.jpg?t=1592993902"
  },
  {
    "internalName": "HEARTSOFIRONIV",
    "title": "Hearts of Iron IV",
    "metacriticLink": "/game/pc/hearts-of-iron-iv",
    "dealID": "26Dh56jhwRygJMqF9YgrTdkxMXb1IOpPEZYfGsvoud4%3D",
    "storeID": "1",
    "gameID": "152738",
    "salePrice": "9.99",
    "normalPrice": "39.99",
    "isOnSale": "1",
    "savings": "75.018755",
    "metacriticScore": "83",
    "steamRatingText": "Very Positive",
    "steamRatingPercent": "92",
    "steamRatingCount": "197911",
    "steamAppID": "394360",
    "releaseDate": 1465171200,
    "lastChange": 1664231048,
    "dealRating": "8.1",
    "thumb": "https://cdn.cloudflare.steamstatic.com/steam/apps/394360/capsule_sm_120_alt_assets_1.jpg?t=1664294433"
  },
  {
    "internalName": "LEGENDSOFEISENWALD",
    "title": "Legends of Eisenwald",
    "metacriticLink": "/game/pc/legends-of-eisenwald",
    "dealID": "9l1YK%2F0gJhHzDE%2FEPfNjrez6itu15bEf3Dc85STzOiA%3D",
    "storeID": "1",
    "gameID": "102227",
    "salePrice": "3.99",
    "normalPrice": "19.99",
    "isOnSale": "1",
    "savings": "80.040020",
    "metacriticScore": "71",
    "steamRatingText": "Mostly Positive",
    "steamRatingPercent": "76",
    "steamRatingCount": "1243",
    "steamAppID": "246760",
    "releaseDate": 1435795200,
    "lastChange": 1664233173,
    "dealRating": "8.1",
    "thumb": "https://cdn.cloudflare.steamstatic.com/steam/apps/246760/capsule_sm_120.jpg?t=1663584490"
  },
  {
    "internalName": "AMERICANCONQUEST",
    "title": "American Conquest",
    "metacriticLink": "/game/pc/american-conquest",
    "dealID": "5iS1OD0X8VrsoUSwcU7w5JkHPTTpSeAzY8c1J3T53vA%3D",
    "storeID": "1",
    "gameID": "291",
    "salePrice": "1.24",
    "normalPrice": "4.99",
    "isOnSale": "1",
    "savings": "75.150301",
    "metacriticScore": "76",
    "steamRatingText": "Mixed",
    "steamRatingPercent": "66",
    "steamRatingCount": "416",
    "steamAppID": "115210",
    "releaseDate": 1044403200,
    "lastChange": 1664233368,
    "dealRating": "8.1",
    "thumb": "https://cdn.cloudflare.steamstatic.com/steam/apps/115210/capsule_sm_120.jpg?t=1568742372"
  },
  {
    "internalName": "SECRETFILES2PURITASCORDIS",
    "title": "Secret Files 2: Puritas Cordis",
    "metacriticLink": "/game/pc/secret-files-2-puritas-cordis",
    "dealID": "Kyhe7EzJisNvcxXyXLZgF31uFRjWT7La6Cno9p6gyIw%3D",
    "storeID": "1",
    "gameID": "1111",
    "salePrice": "1.99",
    "normalPrice": "9.99",
    "isOnSale": "1",
    "savings": "80.080080",
    "metacriticScore": "64",
    "steamRatingText": "Very Positive",
    "steamRatingPercent": "83",
    "steamRatingCount": "129",
    "steamAppID": "40340",
    "releaseDate": 1256774400,
    "lastChange": 1664258125,
    "dealRating": "8.1",
    "thumb": "https://cdn.cloudflare.steamstatic.com/steam/apps/40340/capsule_sm_120.jpg?t=1645612126"
  }
]